hello_user/__init__.py
hello_user/hello.py
hello_world_art256-1.0.0.dist-info/METADATA
hello_world_art256-1.0.0.dist-info/WHEEL
hello_world_art256-1.0.0.dist-info/entry_points.txt
hello_world_art256-1.0.0.dist-info/top_level.txt
hello_world_art256-1.0.0.dist-info/RECORD
