Metadata-Version: 2.1
Name: hello-world-art256
Version: 1.0.0
Summary: Greets the user's name.
Author-email: Arthur Benjamin Angeles <abyangeles28@gmail.com>
